syspass_api_client/__init__.py
syspass_api_client/__version__.py
syspass_api_client/account.py
syspass_api_client/api.py
syspass_api_client/category.py
syspass_api_client/client.py
syspass_api_client/config.py
syspass_api_client/tag.py
syspass_api_client/user_group.py
tests/__init__.py
tests/data_mocks.py
tests/test_account.py
tests/test_api.py
tests/test_category.py
tests/test_client.py
tests/test_config.py
tests/test_tag.py
tests/test_user_group.py
syspass_api_client-0.1.3.dist-info/METADATA
syspass_api_client-0.1.3.dist-info/WHEEL
syspass_api_client-0.1.3.dist-info/top_level.txt
syspass_api_client-0.1.3.dist-info/RECORD
