Metadata-Version: 2.1
Name: syspass-api-client
Version: 0.1.3
Summary: sysPass API client library for Python.
Home-page: https://github.com/sysPass/syspass-api-client-python
Author: Rubén Domínguez
Author-email: nuxsmin@syspass.org
License: Apache 2.0
Project-URL: Source, https://github.com/sysPass/syspass-api-client-python
Platform: UNKNOWN
Classifier: Development Status :: 4 - Beta
Classifier: Intended Audience :: Developers
Classifier: Natural Language :: English
Classifier: License :: OSI Approved :: Apache Software License
Classifier: Operating System :: OS Independent
Classifier: Programming Language :: Python
Classifier: Programming Language :: Python :: 3.5
Classifier: Programming Language :: Python :: 3.6
Classifier: Programming Language :: Python :: 3.7
Classifier: Programming Language :: Python :: Implementation :: CPython
Classifier: Programming Language :: Python :: Implementation :: PyPy
Classifier: Topic :: Software Development :: Libraries :: Python Modules
Requires-Python: >=3.5
Requires-Dist: requests
